[{"id":"16","baseVerbale":"breed","preterit":"bred","participePasse":"bred","traduction":"\u00e9lever (du b\u00e9tail)"},{"id":"55","baseVerbale":"grow","preterit":"grew","participePasse":"grown","traduction":"grandir"},{"id":"13","baseVerbale":"bleed","preterit":"bled","participePasse":"bled","traduction":"saigner"},{"id":"120","baseVerbale":"spell","preterit":"spelt","participePasse":"spelt","traduction":"\u00e9peler"},{"id":"64","baseVerbale":"kneel","preterit":"knelt","participePasse":"knelt","traduction":"s'agenouiller"},{"id":"156","baseVerbale":"weep","preterit":"wept","participePasse":"wept","traduction":"pleurer"},{"id":"67","baseVerbale":"lead","preterit":"led","participePasse":"led","traduction":"mener"},{"id":"144","baseVerbale":"tear","preterit":"tore","participePasse":"torn","traduction":"d\u00e9chirer"},{"id":"124","baseVerbale":"split","preterit":"split","participePasse":"split","traduction":"fendre"},{"id":"18","baseVerbale":"build","preterit":"built","participePasse":"built","traduction":"construire"},{"id":"151","baseVerbale":"understand","preterit":"understood","participePasse":"understood","traduction":"comprendre"},{"id":"62","baseVerbale":"hurt","preterit":"hurt","participePasse":"hurt","traduction":"blesser"},{"id":"108","baseVerbale":"sing","preterit":"sang","participePasse":"sung","traduction":"chanter"},{"id":"47","baseVerbale":"forbid","preterit":"forbade","participePasse":"forbidden","traduction":"interdire"},{"id":"147","baseVerbale":"throw","preterit":"threw","participePasse":"thrown","traduction":"jeter"},{"id":"77","baseVerbale":"make","preterit":"made","participePasse":"made","traduction":"faire, fabriquer"},{"id":"154","baseVerbale":"wear","preterit":"wore","participePasse":"worn","traduction":"porter (des v\u00eatements)"},{"id":"88","baseVerbale":"ring","preterit":"rang","participePasse":"rung","traduction":"sonner"},{"id":"109","baseVerbale":"sink","preterit":"sank","participePasse":"sunk","traduction":"couler"},{"id":"12","baseVerbale":"bite","preterit":"bit","participePasse":"bitten","traduction":"mordre"},{"id":"100","baseVerbale":"shear","preterit":"sheared","participePasse":"shorn","traduction":"tondre (des moutons)"},{"id":"92","baseVerbale":"say","preterit":"said","participePasse":"said","traduction":"dire"},{"id":"49","baseVerbale":"forgive","preterit":"forgave","participePasse":"forgiven","traduction":"pardonner"},{"id":"3","baseVerbale":"awake","preterit":"awoke","participePasse":"awoken","traduction":"(se) r\u00e9veiller"},{"id":"4","baseVerbale":"bear","preterit":"bore","participePasse":"borne","traduction":"supporter"},{"id":"119","baseVerbale":"speed","preterit":"sped","participePasse":"sped","traduction":"aller \u00e0 toute vitesse"},{"id":"70","baseVerbale":"learn","preterit":"learnt","participePasse":"learnt","traduction":"apprendre"},{"id":"46","baseVerbale":"fly","preterit":"flew","participePasse":"flown","traduction":"voler"},{"id":"149","baseVerbale":"tread","preterit":"trod","participePasse":"trodden","traduction":"fouler aux pieds"},{"id":"99","baseVerbale":"shake","preterit":"shook","participePasse":"shaken","traduction":"secouer"},{"id":"26","baseVerbale":"come","preterit":"came","participePasse":"come","traduction":"venir"},{"id":"142","baseVerbale":"take","preterit":"took","participePasse":"taken","traduction":"prendre"},{"id":"35","baseVerbale":"drink","preterit":"drank","participePasse":"drunk","traduction":"boire"},{"id":"128","baseVerbale":"stand","preterit":"stood","participePasse":"stood","traduction":"\u00eatre debout"},{"id":"90","baseVerbale":"run","preterit":"ran","participePasse":"run","traduction":"courir"},{"id":"40","baseVerbale":"feed","preterit":"fed","participePasse":"fed","traduction":"nourrir"},{"id":"138","baseVerbale":"sweep","preterit":"swept","participePasse":"swept","traduction":"balayer"},{"id":"145","baseVerbale":"tell","preterit":"told","participePasse":"told","traduction":"dire, raconter"},{"id":"118","baseVerbale":"speak","preterit":"spoke","participePasse":"spoken","traduction":"parler"},{"id":"45","baseVerbale":"fling","preterit":"flung","participePasse":"flung","traduction":"jeter violemment"},{"id":"110","baseVerbale":"sit","preterit":"sat","participePasse":"sat","traduction":"\u00eatre assis"},{"id":"5","baseVerbale":"beat","preterit":"beat","participePasse":"beaten","traduction":"battre"},{"id":"82","baseVerbale":"pay","preterit":"paid","participePasse":"paid","traduction":"payer"},{"id":"53","baseVerbale":"go","preterit":"went","participePasse":"gone","traduction":"aller"},{"id":"42","baseVerbale":"fight","preterit":"fought","participePasse":"fought","traduction":"combattre"},{"id":"95","baseVerbale":"sell","preterit":"sold","participePasse":"sold","traduction":"vendre"},{"id":"8","baseVerbale":"bend","preterit":"bent","participePasse":"bent","traduction":"(se) courber"},{"id":"150","baseVerbale":"undergo","preterit":"underwent","participePasse":"undergone","traduction":"subir"},{"id":"44","baseVerbale":"flee","preterit":"fled","participePasse":"fled","traduction":"s'enfuir"},{"id":"117","baseVerbale":"sow","preterit":"sowed","participePasse":"sown","traduction":"semer"},{"id":"106","baseVerbale":"shrink","preterit":"shrank","participePasse":"shrunk","traduction":"r\u00e9tr\u00e9cir"},{"id":"143","baseVerbale":"teach","preterit":"taught","participePasse":"taught","traduction":"enseigner"},{"id":"52","baseVerbale":"give","preterit":"gave","participePasse":"given","traduction":"donner"},{"id":"33","baseVerbale":"draw","preterit":"drew","participePasse":"drawn","traduction":"dessiner"},{"id":"122","baseVerbale":"spill","preterit":"spilt","participePasse":"spilt","traduction":"renverser (un liquide)"},{"id":"161","baseVerbale":"write","preterit":"wrote","participePasse":"written","traduction":"\u00e9crire"},{"id":"80","baseVerbale":"mow","preterit":"mowed","participePasse":"mown","traduction":"tondre"},{"id":"7","baseVerbale":"begin","preterit":"began","participePasse":"begun","traduction":"commencer"},{"id":"152","baseVerbale":"upset","preterit":"upset","participePasse":"upset","traduction":"bouleverser"},{"id":"73","baseVerbale":"let","preterit":"let","participePasse":"let","traduction":"permettre, louer"},{"id":"69","baseVerbale":"leap","preterit":"leapt","participePasse":"leapt","traduction":"sauter"},{"id":"54","baseVerbale":"grind","preterit":"ground","participePasse":"ground","traduction":"moudre"},{"id":"9","baseVerbale":"bet","preterit":"bet","participePasse":"bet","traduction":"parier"},{"id":"125","baseVerbale":"spoil","preterit":"spoilt","participePasse":"spoilt","traduction":"g\u00e2cher, g\u00e2ter"},{"id":"22","baseVerbale":"cast","preterit":"cast","participePasse":"cast","traduction":"jeter, lancer"},{"id":"107","baseVerbale":"shut","preterit":"shut","participePasse":"shut","traduction":"fermer"},{"id":"72","baseVerbale":"lend","preterit":"lent","participePasse":"lent","traduction":"pr\u00eater"},{"id":"17","baseVerbale":"bring","preterit":"brought","participePasse":"brought","traduction":"apporter"},{"id":"27","baseVerbale":"cost","preterit":"cost","participePasse":"cost","traduction":"co\u00fbter"},{"id":"43","baseVerbale":"find","preterit":"found","participePasse":"found","traduction":"trouver"},{"id":"31","baseVerbale":"dig","preterit":"dug","participePasse":"dug","traduction":"creuser"},{"id":"34","baseVerbale":"dream","preterit":"dreamt","participePasse":"dreamt","traduction":"r\u00eaver"},{"id":"51","baseVerbale":"get","preterit":"got","participePasse":"got","traduction":"obtenir"},{"id":"159","baseVerbale":"withdraw","preterit":"withdrew","participePasse":"withdrawn","traduction":"(se) retirer"},{"id":"136","baseVerbale":"strive","preterit":"strove","participePasse":"striven","traduction":"s'efforcer"},{"id":"155","baseVerbale":"weave","preterit":"wove","participePasse":"woven","traduction":"tisser"},{"id":"112","baseVerbale":"slide","preterit":"slid","participePasse":"slid","traduction":"glisser"},{"id":"81","baseVerbale":"overcome","preterit":"overcame","participePasse":"overcome","traduction":"surmonter, vaincre"},{"id":"134","baseVerbale":"strike","preterit":"struck","participePasse":"struck","traduction":"frapper"},{"id":"96","baseVerbale":"send","preterit":"sent","participePasse":"sent","traduction":"envoyer"},{"id":"97","baseVerbale":"set","preterit":"set","participePasse":"set","traduction":"fixer"},{"id":"148","baseVerbale":"thrust","preterit":"thrust","participePasse":"thrust","traduction":"enfoncer"},{"id":"132","baseVerbale":"stink","preterit":"stank","participePasse":"stunk","traduction":"puer"},{"id":"30","baseVerbale":"deal","preterit":"dealt","participePasse":"dealt","traduction":"distribuer"},{"id":"139","baseVerbale":"swell","preterit":"swelled","participePasse":"swollen","traduction":"enfler"},{"id":"89","baseVerbale":"rise","preterit":"rose","participePasse":"risen","traduction":"s'\u00e9lever, se lever"},{"id":"115","baseVerbale":"slit","preterit":"slit","participePasse":"slit","traduction":"fendre, inciser"},{"id":"137","baseVerbale":"swear","preterit":"swore","participePasse":"sworn","traduction":"jurer"},{"id":"102","baseVerbale":"shine","preterit":"shone","participePasse":"shone","traduction":"briller"},{"id":"141","baseVerbale":"swing","preterit":"swung","participePasse":"swung","traduction":"se balancer"},{"id":"91","baseVerbale":"saw","preterit":"sawed","participePasse":"sawn","traduction":"scier"},{"id":"74","baseVerbale":"lie","preterit":"lay","participePasse":"lain","traduction":"\u00eatre \u00e9tendu"},{"id":"65","baseVerbale":"know","preterit":"knew","participePasse":"known","traduction":"savoir, conna\u00eetre"},{"id":"71","baseVerbale":"leave","preterit":"left","participePasse":"left","traduction":"laisser, quitter"},{"id":"135","baseVerbale":"string","preterit":"strung","participePasse":"strung","traduction":"enfiler, tendre (une corde)"},{"id":"86","baseVerbale":"rid","preterit":"rid","participePasse":"rid","traduction":"d\u00e9barrasser"},{"id":"37","baseVerbale":"dwell","preterit":"dwelt","participePasse":"dwelt","traduction":"habiter"},{"id":"133","baseVerbale":"stride","preterit":"strode","participePasse":"stridden","traduction":"marcher \u00e0 grands pas"},{"id":"114","baseVerbale":"slink","preterit":"slunk","participePasse":"slunk","traduction":"aller furtivement"},{"id":"28","baseVerbale":"creep","preterit":"crept","participePasse":"crept","traduction":"ramper"},{"id":"123","baseVerbale":"spit","preterit":"spat","participePasse":"spat","traduction":"cracher"},{"id":"24","baseVerbale":"choose","preterit":"chose","participePasse":"chosen","traduction":"choisir"},{"id":"36","baseVerbale":"drive","preterit":"drove","participePasse":"driven","traduction":"conduire"},{"id":"153","baseVerbale":"wake","preterit":"woke","participePasse":"woken","traduction":"(se) r\u00e9veiller"},{"id":"29","baseVerbale":"cut","preterit":"cut","participePasse":"cut","traduction":"couper"},{"id":"60","baseVerbale":"hit","preterit":"hit","participePasse":"hit","traduction":"frapper, atteindre"},{"id":"103","baseVerbale":"shoe","preterit":"shod","participePasse":"shod","traduction":"ferrer, chausser"},{"id":"1","baseVerbale":"abide","preterit":"abode","participePasse":"abode","traduction":"demeurer"},{"id":"121","baseVerbale":"spend","preterit":"spent","participePasse":"spent","traduction":"d\u00e9penser"},{"id":"130","baseVerbale":"stick","preterit":"stuck","participePasse":"stuck","traduction":"coller"},{"id":"105","baseVerbale":"show","preterit":"showed","participePasse":"shown","traduction":"montrer"},{"id":"127","baseVerbale":"spring","preterit":"sprang","participePasse":"sprung","traduction":"jaillir, bondir"},{"id":"75","baseVerbale":"light","preterit":"lit","participePasse":"lit","traduction":"allumer"},{"id":"21","baseVerbale":"buy","preterit":"bought","participePasse":"bought","traduction":"acheter"},{"id":"32","baseVerbale":"do","preterit":"did","participePasse":"done","traduction":"faire"},{"id":"20","baseVerbale":"burst","preterit":"burst","participePasse":"burst","traduction":"\u00e9clater"},{"id":"84","baseVerbale":"quit","preterit":"quit","participePasse":"quit","traduction":"cesser (de)"},{"id":"104","baseVerbale":"shoot","preterit":"shot","participePasse":"shot","traduction":"tirer"},{"id":"57","baseVerbale":"have","preterit":"had","participePasse":"had","traduction":"avoir"},{"id":"79","baseVerbale":"meet","preterit":"met","participePasse":"met","traduction":"(se) rencontrer"},{"id":"66","baseVerbale":"lay","preterit":"laid","participePasse":"laid","traduction":"poser \u00e0 plat"},{"id":"158","baseVerbale":"wind","preterit":"wound","participePasse":"wound","traduction":"enrouler"},{"id":"23","baseVerbale":"catch","preterit":"caught","participePasse":"caught","traduction":"attraper"},{"id":"116","baseVerbale":"smell","preterit":"smelt","participePasse":"smelt","traduction":"sentir (odorat)"},{"id":"157","baseVerbale":"win","preterit":"won","participePasse":"won","traduction":"gagner"},{"id":"126","baseVerbale":"spread","preterit":"spread","participePasse":"spread","traduction":"r\u00e9pandre"},{"id":"14","baseVerbale":"blow","preterit":"blew","participePasse":"blown","traduction":"souffler"},{"id":"113","baseVerbale":"sling","preterit":"slung","participePasse":"slung","traduction":"lancer (avec force)"},{"id":"78","baseVerbale":"mean","preterit":"meant","participePasse":"meant","traduction":"signifier"},{"id":"140","baseVerbale":"swim","preterit":"swam","participePasse":"swum","traduction":"nager"},{"id":"61","baseVerbale":"hold","preterit":"held","participePasse":"held","traduction":"tenir"},{"id":"25","baseVerbale":"cling","preterit":"clung","participePasse":"clung","traduction":"s'accrocher"},{"id":"58","baseVerbale":"hear","preterit":"heard","participePasse":"heard","traduction":"entendre"},{"id":"11","baseVerbale":"bind","preterit":"bound","participePasse":"bound","traduction":"lier, relier"},{"id":"6","baseVerbale":"become","preterit":"became","participePasse":"become","traduction":"devenir"},{"id":"59","baseVerbale":"hide","preterit":"hid","participePasse":"hidden","traduction":"(se) cacher"},{"id":"111","baseVerbale":"sleep","preterit":"slept","participePasse":"slept","traduction":"dormir"},{"id":"2","baseVerbale":"arise","preterit":"arose","participePasse":"arisen","traduction":"s'\u00e9lever, survenir"},{"id":"63","baseVerbale":"keep","preterit":"kept","participePasse":"kept","traduction":"garder"},{"id":"76","baseVerbale":"lose","preterit":"lost","participePasse":"lost","traduction":"perdre"},{"id":"93","baseVerbale":"see","preterit":"saw","participePasse":"seen","traduction":"voir"},{"id":"48","baseVerbale":"forget","preterit":"forgot","participePasse":"forgotten","traduction":"oublier"},{"id":"129","baseVerbale":"steal","preterit":"stole","participePasse":"stolen","traduction":"voler, d\u00e9rober"},{"id":"15","baseVerbale":"break","preterit":"broke","participePasse":"broken","traduction":"casser"},{"id":"68","baseVerbale":"lean","preterit":"leant","participePasse":"leant","traduction":"s'appuyer"},{"id":"83","baseVerbale":"put","preterit":"put","participePasse":"put","traduction":"mettre"},{"id":"98","baseVerbale":"sew","preterit":"sewed","participePasse":"sewn","traduction":"coudre"},{"id":"131","baseVerbale":"sting","preterit":"stung","participePasse":"stung","traduction":"piquer"},{"id":"160","baseVerbale":"wring","preterit":"wrung","participePasse":"wrung","traduction":"tordre"},{"id":"146","baseVerbale":"think","preterit":"thought","participePasse":"thought","traduction":"penser"},{"id":"38","baseVerbale":"eat","preterit":"ate","participePasse":"eaten","traduction":"manger"},{"id":"50","baseVerbale":"freeze","preterit":"froze","participePasse":"frozen","traduction":"geler"},{"id":"56","baseVerbale":"hang","preterit":"hung","participePasse":"hung","traduction":"pendre, accrocher"},{"id":"85","baseVerbale":"read","preterit":"read","participePasse":"read","traduction":"lire"},{"id":"87","baseVerbale":"ride","preterit":"rode","participePasse":"ridden","traduction":"chevaucher"},{"id":"101","baseVerbale":"shed","preterit":"shed","participePasse":"shed","traduction":"verser (des larmes)"},{"id":"94","baseVerbale":"seek","preterit":"sought","participePasse":"sought","traduction":"chercher"},{"id":"19","baseVerbale":"burn","preterit":"burnt","participePasse":"burnt","traduction":"br\u00fbler"},{"id":"41","baseVerbale":"feel","preterit":"felt","participePasse":"felt","traduction":"sentir, \u00e9prouver"},{"id":"10","baseVerbale":"bid","preterit":"bid","participePasse":"bid","traduction":"offrir (un prix)"},{"id":"39","baseVerbale":"fall","preterit":"fell","participePasse":"fallen","traduction":"tomber"}]